alchemistry/__init__.py
alchemistry/__main__.py
alchemistry/cli.py
alchemistry/game.py
alchemistry/helpers.py
alchemistry/recipe_helper.py
alchemistry-0.2.0.dist-info/WHEEL
alchemistry-0.2.0.dist-info/entry_points.txt
alchemistry-0.2.0.dist-info/METADATA
alchemistry-0.2.0.dist-info/RECORD
