Metadata-Version: 2.4
Name: alchemistry
Version: 0.2.0
Summary: A terminal alchemy game where you just make stuff and see how it turns out.
License-Expression: MIT
Requires-Dist: requests~=2.32
Requires-Python: >=3.10
